obj2cli/__init__.py
obj2cli/_cli.py
obj2cli/_cli_click.py
obj2cli/argparse.py
obj2cli/main.py
obj2cli/parser.py
obj2cli/version.py
obj2cli/template/argparse_cli.j2
obj2cli/template/click_cli.j2
obj2cli/template/obj2cli_cli.j2
obj2cli-0.0.4.dist-info/LICENSE
obj2cli-0.0.4.dist-info/METADATA
obj2cli-0.0.4.dist-info/WHEEL
obj2cli-0.0.4.dist-info/entry_points.txt
obj2cli-0.0.4.dist-info/top_level.txt
obj2cli-0.0.4.dist-info/RECORD
