Metadata-Version: 2.1
Name: obj2cli
Version: 0.0.4
Summary: convert object/class to CLI command
Home-page: https://github.com/wtnb75/obj2cli
Author: Takashi WATANABE
Author-email: wtnb75@gmail.com
License: MIT
Platform: UNKNOWN
Classifier: Development Status :: 3 - Alpha
Classifier: Intended Audience :: Developers
Classifier: License :: OSI Approved :: MIT License
Classifier: Programming Language :: Python :: 3
Requires-Dist: Click
Requires-Dist: argparse-utils
Requires-Dist: PyYAML
Requires-Dist: toml
Requires-Dist: Jinja2
